Workbook

Sheet Trial Balance & Mapping
A2: ABC MANUFACTURING PVT. LTD.
A3: Trial Balance with Schedule III (Division I - AS Framework) Mapping | FY 2025-26 & FY 2024-25
A4: Reporting Unit: ₹ in Lakhs | CIN: U74999MH2010PTC203456
A6: GL Code | B6: GL Account Description | C6: Account Type | D6: CY Debit (₹) | E6: CY Credit (₹) | F6: PY Debit (₹) | G6: PY Credit (₹) | H6: CY Net Amount | I6: PY Net Amount | J6: Schedule III Statement | K6: Major Head | L6: Minor Head / Line Item | M6: Note No.
A7: 101001 | B7: Equity Share Capital (Face Value ₹10) | C7: Equity | D7: 0 | E7: 20 | F7: 0 | G7: 20 | H7: =D7-E7 -> -20 | I7: =F7-G7 -> -20 | J7: Balance Sheet | K7: Equity and Liabilities | L7: Share Capital | M7: 1
A8: 102001 | B8: General Reserve | C8: Equity | D8: 0 | E8: 15 | F8: 0 | G8: 15 | H8: =D8-E8 -> -15 | I8: =F8-G8 -> -15 | J8: Balance Sheet | K8: Equity and Liabilities | L8: Other Equity | M8: 2
A9: 102002 | B9: Surplus / Retained Earnings (Opening) | C9: Equity | D9: 0 | E9: 13 | F9: 0 | G9: 8 | H9: =D9-E9 -> -13 | I9: =F9-G9 -> -8 | J9: Balance Sheet | K9: Equity and Liabilities | L9: Other Equity | M9: 2
A10: 201001 | B10: Term Loan from HDFC Bank (Secured) | C10: Non-Current Liability | D10: 0 | E10: 10 | F10: 0 | G10: 12 | H10: =D10-E10 -> -10 | I10: =F10-G10 -> -12 | J10: Balance Sheet | K10: Equity and Liabilities | L10: Long-Term Borrowings | M10: 3
A11: 201002 | B11: Deferred Tax Liabilities (Net) | C11: Non-Current Liability | D11: 0 | E11: 3.5 | F11: 0 | G11: 4 | H11: =D11-E11 -> -3.5 | I11: =F11-G11 -> -4 | J11: Balance Sheet | K11: Equity and Liabilities | L11: Deferred Tax Liabilities (Net) | M11: 3
A12: 201003 | B12: Provision for Employee Retirement Benefits | C12: Non-Current Liability | D12: 0 | E12: 1.5 | F12: 0 | G12: 2 | H12: =D12-E12 -> -1.5 | I12: =F12-G12 -> -2 | J12: Balance Sheet | K12: Equity and Liabilities | L12: Long-Term Provisions | M12: 3
A13: 202001 | B13: Cash Credit / Working Capital Facility (SBI) | C13: Current Liability | D13: 0 | E13: 12 | F13: 0 | G13: 10 | H13: =D13-E13 -> -12 | I13: =F13-G13 -> -10 | J13: Balance Sheet | K13: Equity and Liabilities | L13: Short-Term Borrowings | M13: 4
A14: 202002 | B14: Sundry Creditors for Raw Materials (MSME) | C14: Current Liability | D14: 0 | E14: 8.5 | F14: 0 | G14: 7 | H14: =D14-E14 -> -8.5 | I14: =F14-G14 -> -7 | J14: Balance Sheet | K14: Equity and Liabilities | L14: Trade Payables | M14: 4
A15: 202003 | B15: Sundry Creditors for Operational Expenses | C15: Current Liability | D15: 0 | E15: 6.5 | F15: 0 | G15: 6 | H15: =D15-E15 -> -6.5 | I15: =F15-G15 -> -6 | J15: Balance Sheet | K15: Equity and Liabilities | L15: Trade Payables | M15: 4
A16: 202004 | B16: Advance Received from Customers | C16: Current Liability | D16: 0 | E16: 3 | F16: 0 | G16: 2.5 | H16: =D16-E16 -> -3 | I16: =F16-G16 -> -2.5 | J16: Balance Sheet | K16: Equity and Liabilities | L16: Other Current Liabilities | M16: 4
A17: 202005 | B17: Statutory Dues Payable (GST & TDS) | C17: Current Liability | D17: 0 | E17: 2.2 | F17: 0 | G17: 2 | H17: =D17-E17 -> -2.2 | I17: =F17-G17 -> -2 | J17: Balance Sheet | K17: Equity and Liabilities | L17: Other Current Liabilities | M17: 4
A18: 202006 | B18: Provision for Income Tax (Current Year) | C18: Current Liability | D18: 0 | E18: 2.8 | F18: 0 | G18: 2.5 | H18: =D18-E18 -> -2.8 | I18: =F18-G18 -> -2.5 | J18: Balance Sheet | K18: Equity and Liabilities | L18: Short-Term Provisions | M18: 4
... A38: 102003 | B38: Current Year Profit Transferred to Reserves | C38: Equity | D38: 7 | E38: 0 | F38: 0 | G38: 0 | H38: =D38-E38 -> 7 | I38: =F38-G38 -> 0 | J38: Balance Sheet | K38: Equity and Liabilities | L38: Other Equity | M38: 2
B39: TOTAL TRIAL BALANCE | D39: =SUM(D7:D38) -> 231 | E39: =SUM(E7:E38) -> 231 | F39: =SUM(F7:F38) -> 206 | G39: =SUM(G7:G38) -> 206 | H39: =SUM(H7:H38) -> 0 | I39: =SUM(I7:I38) -> 0
B41: Trial Balance Validation Status: | D41: =IF(ROUND(D39-E39,2)=0,"✓ CY BALANCED","❌ OUT OF BALANCE") -> ✓ CY BALANCED | F41: =IF(ROUND(F39-G39,2)=0,"✓ PY BALANCED","❌ OUT OF BALANCE") -> ✓ PY BALANCED

Sheet Schedule III - Balance Sheet
B2: ABC MANUFACTURING PVT. LTD.
B3: BALANCE SHEET AS AT 31 MARCH 2026
B4: (₹ in lakh) | Division I - Accounting Standards (AS Framework)
B6: Particulars | C6: Note No. | D6: As at 31 March 2026 | E6: As at 31 March 2025
B7: I. EQUITY AND LIABILITIES
B8: (1) Shareholders' Funds
B9: (a) Share capital | C9: 1 | D9: ='Trial Balance & Mapping'!E7 -> 20 | E9: ='Trial Balance & Mapping'!G7 -> 20
B10: (b) Reserves and surplus | C10: 2 | D10: ='Trial Balance & Mapping'!E8+'Trial Balance & Mapping'!E9+'Trial Balance & Mapping'!D32 -> 50 | E10: ='Trial Balance & Mapping'!G8+'Trial Balance & Mapping'!G9 -> 23
B11: (2) Non-Current Liabilities
B12: (a) Long-term borrowings | C12: 3 | D12: ='Trial Balance & Mapping'!E10 -> 10 | E12: ='Trial Balance & Mapping'!G10 -> 12
B13: (b) Deferred tax liabilities (Net) | C13: 3 | D13: ='Trial Balance & Mapping'!E11 -> 3.5 | E13: ='Trial Balance & Mapping'!G11 -> 4
B14: (c) Long-term provisions | C14: 3 | D14: ='Trial Balance & Mapping'!E12 -> 1.5 | E14: ='Trial Balance & Mapping'!G12 -> 2
B15: (3) Current Liabilities
B16: (a) Short-term borrowings | C16: 4 | D16: ='Trial Balance & Mapping'!E13 -> 12 | E16: ='Trial Balance & Mapping'!G13 -> 10
B17: (b) Trade payables | C17: 4 | D17: ='Trial Balance & Mapping'!E14+'Trial Balance & Mapping'!E15 -> 15 | E17: ='Trial Balance & Mapping'!G14+'Trial Balance & Mapping'!G15 -> 13
B18: (c) Other current liabilities | C18: 4 | D18: ='Trial Balance & Mapping'!E16+'Trial Balance & Mapping'!E17 -> 5.2 | E18: ='Trial Balance & Mapping'!G16+'Trial Balance & Mapping'!G17 -> 4.5
B19: (d) Short-term provisions | C19: 4 | D19: ='Trial Balance & Mapping'!E18 -> 2.8 | E19: ='Trial Balance & Mapping'!G18 -> 2.5
B20: TOTAL EQUITY AND LIABILITIES | D20: =SUM(D9:D10,D12:D14,D16:D19) -> 120 | E20: =SUM(E9:E10,E12:E14,E16:E19) -> 91
B21: II. ASSETS
B22: (1) Non-Current Assets
B23: (a) Property, Plant and Equipment | C23: 5 | D23: ='Trial Balance & Mapping'!D19+'Trial Balance & Mapping'!D20-'Trial Balance & Mapping'!E21 -> 43 | E23: ='Trial Balance & Mapping'!F19+'Trial Balance & Mapping'!F20-'Trial Balance & Mapping'!G21 -> 39.5
B24: (b) Capital work-in-progress | C24: 5 | D24: ='Trial Balance & Mapping'!D22 -> 3 | E24: ='Trial Balance & Mapping'!F22 -> 2.5
B25: (c) Long-term loans and advances | C25: 5 | D25: ='Trial Balance & Mapping'!D23 -> 2 | E25: ='Trial Balance & Mapping'!F23 -> 2
B26: (2) Current Assets
B27: (a) Inventories | C27: 6 | D27: ='Trial Balance & Mapping'!D24+'Trial Balance & Mapping'!D25 -> 28 | E27: ='Trial Balance & Mapping'!F24+'Trial Balance & Mapping'!F25 -> 25
B28: (b) Trade receivables | C28: 6 | D28: ='Trial Balance & Mapping'!D26 -> 20 | E28: ='Trial Balance & Mapping'!F26 -> 18
B29: (c) Cash and cash equivalents | C29: 6 | D29: ='Trial Balance & Mapping'!D27 -> 6.5 | E29: ='Trial Balance & Mapping'!F27 -> 6
B30: (d) Short-term loans and advances | C30: 6 | D30: ='Trial Balance & Mapping'!D28 -> 2.5 | E30: ='Trial Balance & Mapping'!F28 -> 3
B31: TOTAL ASSETS | D31: =SUM(D23:D25,D27:D30) -> 105 | E31: =SUM(E23:E25,E27:E30) -> 96
B33: Balance Sheet Cross-Check (Assets - Liabilities): | D33: =IF(ROUND(D31-D20,2)=0,"✓ CY BALANCED (105.00)","❌ MISMATCH") -> ❌ MISMATCH | E33: =IF(ROUND(E31-E20,2)=0,"✓ PY BALANCED (96.00)","❌ MISMATCH") -> ❌ MISMATCH

Sheet Notes to Accounts
B2: ABC MANUFACTURING PVT. LTD.
B3: NOTES FORMING PART OF THE FINANCIAL STATEMENTS
B4: Figures in ₹ Lakhs | Comparative Figures for Previous Year included
B6: Note No. | C6: Particulars / Line Item Breakdown | D6: As at 31 March 2026 | E6: As at 31 March 2025
B7: 1 | C7: Note 1: Share Capital
C8: Authorised: 3,00,000 Equity Shares of ₹10 each | D8: 30 | E8: 30
C9: Issued, Subscribed & Paid-up: 2,00,000 Equity Shares of ₹10 each | D9: 20 | E9: 20
C10: Total Share Capital | D10: =D9 -> 20 | E10: =E9 -> 20
B11: 2 | C11: Note 2: Reserves and Surplus
C12: General Reserve (Opening & Closing) | D12: 15 | E12: 15
C13: Surplus in Statement of Profit and Loss (Opening) | D13: 13 | E13: 8
C14: Add: Profit for the Year | D14: 7 | E14: 5
C15: Closing Balance in Profit and Loss | D15: =D13+D14 -> 20 | E15: =E13+E14 -> 13
C16: Total Reserves and Surplus | D16: =D12+D15 -> 35 | E16: =E12+E15 -> 28
B17: 3 | C17: Note 3: Non-Current Liabilities
C18: Term Loan from HDFC Bank (Secured against plant) | D18: 10 | E18: 12
C19: Deferred Tax Liabilities (Net) | D19: 3.5 | E19: 4
C20: Provision for Employee Retirement Benefits (Gratuity/Leave) | D20: 1.5 | E20: 2
C21: Total Non-Current Liabilities | D21: =SUM(D18:D20) -> 15 | E21: =SUM(E18:E20) -> 18
B22: 4 | C22: Note 4: Current Liabilities
C23: Working Capital Borrowings (SBI Cash Credit) | D23: 12 | E23: 10
C24: Trade Payables - MSME Enterprises | D24: 8.5 | E24: 7
C25: Trade Payables - Other than MSME | D25: 6.5 | E25: 6
C26: Advance Received from Customers | D26: 3 | E26: 2.5
C27: Statutory Liabilities (GST, TDS & PF Payable) | D27: 2.2 | E27: 2
C28: Provision for Current Tax | D28: 2.8 | E28: 2.5
C29: Total Current Liabilities | D29: =SUM(D23:D28) -> 35 | E29: =SUM(E23:E28) -> 30
B30: 5 | C30: Note 5: Non-Current Assets
C31: Plant & Machinery (Gross Block: ₹42.00, Acc. Dep: ₹11.00) | D31: 31 | E31: 29.5
C32: Factory Equipment & Tools | D32: 12 | E32: 10
C33: Capital Work-in-Progress (Machinery awaiting commissioning) | D33: 3 | E33: 2.5
C34: Long-term Security Deposits (Govt & Utilities) | D34: 2 | E34: 2
C35: Total Non-Current Assets | D35: =SUM(D31:D34) -> 48 | E35: =SUM(E31:E34) -> 44
B36: 6 | C36: Note 6: Current Assets
C37: Raw Materials & Packing Materials | D37: 16 | E37: 14
C38: Finished Goods | D38: 12 | E38: 11
C39: Trade Receivables (Unsecured, considered good) | D39: 20 | E39: 18
C40: Cash and Cash Equivalents (Bank Current Accounts) | D40: 6.5 | E40: 6
C41: Short-Term Loans and Advances (Prepaid expenses) | D41: 2.5 | E41: 3
C42: Total Current Assets | D42: =SUM(D37:D41) -> 57 | E42: =SUM(E37:E41) -> 52
